oect_transfer_analysis/__init__.py
oect_transfer_analysis/animation.py
oect_transfer_analysis/data_loader.py
oect_transfer_analysis/time_series.py
oect_transfer_analysis/utils.py
oect_transfer_analysis/visualization.py
oect_transfer_analysis-1.0.3.dist-info/licenses/LICENSE
oect_transfer_analysis-1.0.3.dist-info/METADATA
oect_transfer_analysis-1.0.3.dist-info/WHEEL
oect_transfer_analysis-1.0.3.dist-info/top_level.txt
oect_transfer_analysis-1.0.3.dist-info/RECORD
