Metadata-Version: 2.4
Name: oect-transfer-analysis
Version: 1.0.3
Summary: Advanced analysis tools for OECT transfer curves - time series analysis, visualization, and animation
Home-page: https://github.com/yourusername/oect-transfer-analysis
Author: lidonghao
Author-email: lidonghao <lidonghao100@outlook.com>
License: MIT
Project-URL: Homepage, https://github.com/yourusername/oect-transfer-analysis
Project-URL: Documentation, https://oect-transfer-analysis.readthedocs.io/
Project-URL: Repository, https://github.com/yourusername/oect-transfer-analysis.git
Project-URL: Bug Tracker, https://github.com/yourusername/oect-transfer-analysis/issues
Keywords: oect,transfer,analysis,visualization,time-series,animation
Classifier: Intended Audience :: Science/Research
Classifier: License :: OSI Approved :: MIT License
Classifier: Programming Language :: Python :: 3
Classifier: Programming Language :: Python :: 3.8
Classifier: Programming Language :: Python :: 3.9
Classifier: Programming Language :: Python :: 3.10
Classifier: Programming Language :: Python :: 3.11
Classifier: Topic :: Scientific/Engineering :: Visualization
Classifier: Topic :: Scientific/Engineering :: Physics
Requires-Python: >=3.8
License-File: LICENSE
Requires-Dist: oect-transfer>=0.4.2
Requires-Dist: numpy>=1.20.0
Requires-Dist: pandas>=1.3.0
Requires-Dist: matplotlib>=3.5.0
Provides-Extra: animation
Requires-Dist: opencv-python>=4.5.0; extra == "animation"
Requires-Dist: Pillow>=8.0.0; extra == "animation"
Provides-Extra: dev
Requires-Dist: black>=22.0; extra == "dev"
Requires-Dist: flake8>=4.0; extra == "dev"
Requires-Dist: mypy>=0.950; extra == "dev"
Requires-Dist: pytest>=6.0; extra == "dev"
Requires-Dist: pytest-cov>=2.0; extra == "dev"
Requires-Dist: build; extra == "dev"
Provides-Extra: docs
Requires-Dist: sphinx>=4.0; extra == "docs"
Requires-Dist: sphinx-rtd-theme>=1.0; extra == "docs"
Requires-Dist: myst-parser>=0.17; extra == "docs"
Provides-Extra: all
Requires-Dist: opencv-python>=4.5.0; extra == "all"
Requires-Dist: Pillow>=8.0.0; extra == "all"
Dynamic: author
Dynamic: home-page
Dynamic: license-file
Dynamic: requires-python
